mosses/__init__.py
mosses/heatmap.py
mosses/predictive_validity.py
mosses/core/__init__.py
mosses/core/evaluator.py
mosses/core/helpers.py
mosses/core/metrics.py
mosses/core/plotter.py
mosses-0.2.11.dist-info/licenses/AUTHORS.md
mosses-0.2.11.dist-info/licenses/LICENSE.md
mosses-0.2.11.dist-info/METADATA
mosses-0.2.11.dist-info/WHEEL
mosses-0.2.11.dist-info/top_level.txt
mosses-0.2.11.dist-info/RECORD
