Metadata-Version: 2.4
Name: mosses
Version: 0.2.11
Summary: Set of functionalities to assess molecular property prediction models.
Author-email: Vigneshwari Subramanian <vignesh.bioinfo@gmail.com>, Gian Marco Ghiandoni <ghiandoni.g@gmail.com>
License: Apache v2.0
Requires-Python: >=3.10
License-File: LICENSE.md
License-File: AUTHORS.md
Requires-Dist: numpy
Requires-Dist: pandas
Requires-Dist: scipy
Requires-Dist: matplotlib
Requires-Dist: scikit-learn
Requires-Dist: colorama
Requires-Dist: seaborn
Requires-Dist: pyyaml
Requires-Dist: statsmodels
Requires-Dist: jinja2
Provides-Extra: dev
Requires-Dist: pytest; extra == "dev"
Requires-Dist: pre-commit; extra == "dev"
Dynamic: license-file
